LICENSE
README.md
lyytext.py
setup.py
lyytext.egg-info/PKG-INFO
lyytext.egg-info/SOURCES.txt
lyytext.egg-info/dependency_links.txt
lyytext.egg-info/top_level.txt