Metadata-Version: 2.1
Name: lyytext
Version: 1.6
Summary: userfull application for  lyy
Author: lyy
Author-email: 
License: MIT
License-File: LICENSE
